smileml/__init__.py
smileml/ace.py
smileml/ace.r
smileml/impact.py
smileml/lime.py
smileml/metrics.py
smileml/pipeline.py
smileml/pipelinebase.py
smileml/stacking.py
smileml/utils.py
smileml/feature_extraction/__init__.py
smileml/feature_extraction/preprocessing.py
smileml/feature_extraction/target_encode.py
smileml/misc/__init__.py
smileml/misc/googleapi.py
smileml/ml/__init__.py
smileml/ml/hyperband.py
smileml/ml/lightgbm.py
smileml/ml/preprocessing.py
smileml/ml/random_layer.py
smileml/ml/randombits.py
smileml/ml/xgboost.py
smileml-0.1.2.dist-info/METADATA
smileml-0.1.2.dist-info/RECORD
smileml-0.1.2.dist-info/WHEEL
smileml-0.1.2.dist-info/top_level.txt
